{
	"info": {
		"_postman_id": "product-management-api",
		"name": "Product Management API",
		"description": "REST API collection for Product Management System",
		"schema": "https://schema.getpostman.com/json/collection/v2.1.0/collection.json"
	},
	"item": [
		{
			"name": "Products",
			"item": [
				{
					"name": "Get All Products",
					"request": {
						"method": "GET",
						"header": [],
						"url": {
							"raw": "{{base_url}}/api/products",
							"host": [
								"{{base_url}}"
							],
							"path": [
								"api",
								"products"
							]
						},
						"description": "Retrieve all products from the database"
					},
					"response": []
				},
				{
					"name": "Get Single Product",
					"request": {
						"method": "GET",
						"header": [],
						"url": {
							"raw": "{{base_url}}/api/products/1",
							"host": [
								"{{base_url}}"
							],
							"path": [
								"api",
								"products",
								"1"
							]
						},
						"description": "Retrieve a specific product by ID"
					},
					"response": []
				},
				{
					"name": "Create Product",
					"request": {
						"method": "POST",
						"header": [
							{
								"key": "Content-Type",
								"value": "application/json"
							}
						],
						"body": {
							"mode": "raw",
							"raw": "{\n    \"name\": \"New Product\",\n    \"description\": \"Product description\",\n    \"price\": 49.99,\n    \"category\": \"Electronics\",\n    \"stock_quantity\": 10\n}"
						},
						"url": {
							"raw": "{{base_url}}/api/products",
							"host": [
								"{{base_url}}"
							],
							"path": [
								"api",
								"products"
							]
						},
						"description": "Create a new product"
					},
					"response": []
				},
				{
					"name": "Update Product",
					"request": {
						"method": "PUT",
						"header": [
							{
								"key": "Content-Type",
								"value": "application/json"
							}
						],
						"body": {
							"mode": "raw",
							"raw": "{\n    \"name\": \"Updated Product Name\",\n    \"price\": 59.99,\n    \"stock_quantity\": 20\n}"
						},
						"url": {
							"raw": "{{base_url}}/api/products/1",
							"host": [
								"{{base_url}}"
							],
							"path": [
								"api",
								"products",
								"1"
							]
						},
						"description": "Update an existing product"
					},
					"response": []
				},
				{
					"name": "Delete Product",
					"request": {
						"method": "DELETE",
						"header": [],
						"url": {
							"raw": "{{base_url}}/api/products/1",
							"host": [
								"{{base_url}}"
							],
							"path": [
								"api",
								"products",
								"1"
							]
						},
						"description": "Delete a product by ID"
					},
					"response": []
				}
			]
		},
		{
			"name": "Categories",
			"item": [
				{
					"name": "Get All Categories",
					"request": {
						"method": "GET",
						"header": [],
						"url": {
							"raw": "{{base_url}}/api/categories",
							"host": [
								"{{base_url}}"
							],
							"path": [
								"api",
								"categories"
							]
						},
						"description": "Retrieve all categories"
					},
					"response": []
				},
				{
					"name": "Get Products by Category",
					"request": {
						"method": "GET",
						"header": [],
						"url": {
							"raw": "{{base_url}}/api/categories/1/products",
							"host": [
								"{{base_url}}"
							],
							"path": [
								"api",
								"categories",
								"1",
								"products"
							]
						},
						"description": "Retrieve all products in a specific category"
					},
					"response": []
				}
			]
		}
	],
	"variable": [
		{
			"key": "base_url",
			"value": "http://localhost/phpAPI",
			"type": "string"
		}
	]
}

